sync2llmtxt/__init__.py
sync2llmtxt/directory_tree.py
sync2llmtxt/sync2llmtxt.py
sync2llmtxt-0.1.0.dist-info/licenses/LICENSE
sync2llmtxt-0.1.0.dist-info/METADATA
sync2llmtxt-0.1.0.dist-info/WHEEL
sync2llmtxt-0.1.0.dist-info/entry_points.txt
sync2llmtxt-0.1.0.dist-info/top_level.txt
sync2llmtxt-0.1.0.dist-info/RECORD
