Metadata-Version: 2.4
Name: sync2llmtxt
Version: 0.1.0
Summary: Automatically aggregate source code files into a single text file for LLM context
Author-email: Author <your.email@example.com>
License-Expression: MIT
Project-URL: Homepage, https://github.com/yourusername/sync2llmtxt
Project-URL: Bug Tracker, https://github.com/yourusername/sync2llmtxt/issues
Classifier: Programming Language :: Python :: 3
Classifier: Operating System :: OS Independent
Requires-Python: >=3.7
License-File: LICENSE
Requires-Dist: watchdog
Requires-Dist: throttle
Requires-Dist: PyYAML
Requires-Dist: gitignore_parser
Dynamic: license-file
